higra/__init__.py
higra/concept.py
higra/data_cache.py
higra/hg_utils.py
higra/higram.cpython-313-x86_64-linux-gnu.so
higra/sorting.py
higra/accumulator/__init__.py
higra/accumulator/at_accumulator.py
higra/accumulator/graph_accumulator.py
higra/accumulator/tree_accumulator.py
higra/accumulator/tree_contour_accumulator.py
higra/algo/__init__.py
higra/algo/alignment.py
higra/algo/bipartite_graph.py
higra/algo/graph_core.py
higra/algo/graph_weights.py
higra/algo/horizontal_cuts.py
higra/algo/rag.py
higra/algo/tree.py
higra/algo/tree_energy_optimization.py
higra/algo/tree_fusion.py
higra/algo/tree_monotonic_regression.py
higra/algo/watershed.py
higra/assessment/__init__.py
higra/assessment/fragmentation_curve.py
higra/assessment/hierarchical_cost.py
higra/attribute/__init__.py
higra/attribute/graph_attributes.py
higra/attribute/tree_attributes.py
higra/hierarchy/__init__.py
higra/hierarchy/binary_partition_tree.py
higra/hierarchy/component_tree.py
higra/hierarchy/constrained_connectivity_hierarchy.py
higra/hierarchy/hierarchy_core.py
higra/hierarchy/random_hierarchy.py
higra/hierarchy/watershed_hierarchy.py
higra/image/__init__.py
higra/image/contour_2d.py
higra/image/graph_image.py
higra/image/hierarchy_mean_pb.py
higra/image/image_utils.py
higra/image/tree_of_shapes.py
higra/include/higra/config.hpp
higra/include/higra/graph.hpp
higra/include/higra/sorting.hpp
higra/include/higra/utils.hpp
higra/include/higra/accumulator/accumulator.hpp
higra/include/higra/accumulator/at_accumulator.hpp
higra/include/higra/accumulator/graph_accumulator.hpp
higra/include/higra/accumulator/tree_accumulator.hpp
higra/include/higra/accumulator/tree_contour_accumulator.hpp
higra/include/higra/algo/alignment.hpp
higra/include/higra/algo/bipartite_graph.hpp
higra/include/higra/algo/graph_core.hpp
higra/include/higra/algo/graph_weights.hpp
higra/include/higra/algo/horizontal_cuts.hpp
higra/include/higra/algo/rag.hpp
higra-0.6.13.dist-info/METADATA
higra-0.6.13.dist-info/WHEEL
higra-0.6.13.dist-info/top_level.txt
higra-0.6.13.dist-info/RECORD
higra-0.6.13.dist-info/licenses/LICENSE
