Metadata-Version: 2.4
Name: higra
Version: 0.6.13
Summary: Hierarchical Graph Analysis
Home-page: https://github.com/higra/Higra
Author: Benjamin Perret
Author-email: benjamin.perret@esiee.fr
License: CeCILL-B
License-File: LICENSE
Requires-Dist: numpy>=2.1.3
Dynamic: author
Dynamic: author-email
Dynamic: description
Dynamic: description-content-type
Dynamic: home-page
Dynamic: license
Dynamic: license-file
Dynamic: requires-dist
Dynamic: summary
